odoo8_addon_product_variant_uos-8.0.1.0.0-py2.7-nspkg.pth
odoo8_addon_product_variant_uos-8.0.1.0.0.dist-info/DESCRIPTION.rst
odoo8_addon_product_variant_uos-8.0.1.0.0.dist-info/METADATA
odoo8_addon_product_variant_uos-8.0.1.0.0.dist-info/RECORD
odoo8_addon_product_variant_uos-8.0.1.0.0.dist-info/WHEEL
odoo8_addon_product_variant_uos-8.0.1.0.0.dist-info/metadata.json
odoo8_addon_product_variant_uos-8.0.1.0.0.dist-info/namespace_packages.txt
odoo8_addon_product_variant_uos-8.0.1.0.0.dist-info/top_level.txt
odoo_addons/product_variant_uos/README.rst
odoo_addons/product_variant_uos/__init__.py
odoo_addons/product_variant_uos/__openerp__.py
odoo_addons/product_variant_uos/product.py
odoo_addons/product_variant_uos/images/product_uos.png
odoo_addons/product_variant_uos/static/description/icon.png
odoo_addons/product_variant_uos/tests/__init__.py
odoo_addons/product_variant_uos/tests/test_product.py
